differential-0.6.7.dist-info/METADATA
differential-0.6.7.dist-info/WHEEL
differential-0.6.7.dist-info/entry_points.txt
differential-0.6.7.dist-info/licenses/LICENSE
differential/__init__.py
differential/base_plugin.py
differential/commands.py
differential/constants.py
differential/main.py
differential/plugin_loader.py
differential/plugin_register.py
differential/plugins/__init__.py
differential/plugins/chdbits.py
differential/plugins/chdbits_encode.py
differential/plugins/gazelle.py
differential/plugins/greatposterwall.py
differential/plugins/hdbits.py
differential/plugins/nexusphp.py
differential/plugins/pterclub.py
differential/plugins/ptp.py
differential/plugins/unit3d.py
differential/tools/BDinfoCli.0.7.3/BDInfo.exe
differential/tools/BDinfoCli.0.7.3/DiscUtils.Common.dll
differential/tools/BDinfoCli.0.7.3/DiscUtils.dll
differential/tools/BDinfoCli.0.7.3/Microsoft.WindowsAPICodePack.Shell.dll
differential/tools/BDinfoCli.0.7.3/Microsoft.WindowsAPICodePack.ShellExtensions.dll
differential/tools/BDinfoCli.0.7.3/Microsoft.WindowsAPICodePack.dll
differential/tools/BDinfoCli.0.7.3/ZedGraph.dll
differential/tools/__init__.py
differential/torrent.py
differential/utils/__init__.py
differential/utils/binary.py
differential/utils/browser.py
differential/utils/config.py
differential/utils/image/__init__.py
differential/utils/image/byr.py
differential/utils/image/chevereto.py
differential/utils/image/cloudinary.py
differential/utils/image/hdbits.py
differential/utils/image/imgbox.py
differential/utils/image/imgurl.py
differential/utils/image/lsky.py
differential/utils/image/ptpimg.py
differential/utils/image/smms.py
differential/utils/image/types.py
differential/utils/mediainfo.py
differential/utils/mediainfo_handler.py
differential/utils/nfo.py
differential/utils/parse.py
differential/utils/ptgen/bangumi.py
differential/utils/ptgen/base.py
differential/utils/ptgen/douban.py
differential/utils/ptgen/epic.py
differential/utils/ptgen/imdb.py
differential/utils/ptgen/indienova.py
differential/utils/ptgen/parser.py
differential/utils/ptgen/steam.py
differential/utils/ptgen_handler.py
differential/utils/screenshot_handler.py
differential-0.6.7.dist-info/RECORD
