Metadata-Version: 2.1
Name: Differential
Version: 0.6.7
Summary: A Python script for easy uploading torrents to various PT sites.
Keywords: PT,mediainfo,ptgen,ptpimg
Author-Email: Lei Shi <me@leishi.io>
License: MIT
Classifier: Environment :: Console
Classifier: Operating System :: MacOS
Classifier: Operating System :: POSIX :: Linux
Classifier: Operating System :: Microsoft :: Windows
Classifier: Operating System :: OS Independent
Classifier: Programming Language :: Python :: 3.9
Classifier: Programming Language :: Python :: 3.10
Classifier: Programming Language :: Python :: 3.11
Classifier: Programming Language :: Python :: 3.12
Classifier: License :: OSI Approved :: MIT License
Requires-Python: >=3.9
Requires-Dist: loguru
Requires-Dist: requests
Requires-Dist: lxml
Requires-Dist: Pillow>=9.0.0
Requires-Dist: pymediainfo>=7.0.0
Requires-Dist: torf>=4.3.0
Requires-Dist: bencode.py==4.0.0
